{"id":265286,"name":"Bane, God of Deserts, Leadership and Discipline","created_at":"2024-10-18T05:27:33.000000Z","updated_at":"2024-10-21T08:20:14.000000Z","is_private":0,"note_id":265268,"entity":{"id":6810339,"entity_id":265286,"parent_id":null,"type_id":6,"name":"Bane, God of Deserts, Leadership and Discipline","type":null,"entry":"<p><br><\/p><hr><ul><li>Conservative, Unifying: Advocates for strong, centralized governance<\/li><li>Appearance: A dark, armored figure with a face obscured by shadow<\/li><li>Personality: Domineering, strategic, and ruthlessly efficient<\/li><li>Church: Trains military leaders, advises conquerors, and promotes strict societal order<br><br><\/li><\/ul><ul><li>Edicts: Conquer, impose order, crush defiance.<br><\/li><li>Anathema: Show mercy, tolerate rebellion.<br> <\/li><li>Domains: Tyranny, Destruction, Might, Ambition, Dust<\/li><li>Divine Font: Harm.<br><\/li><li>Sanctification: Unholy.<br><\/li><li>Favored Animal: Green-eyed cat or panther<br><\/li><li>Favored Creature: Minotaur.<br><\/li><li>Favored Material: Iron.<br><\/li><li>Favored Color: Black.<br><\/li><li>Favored Weapon: Morningstar, Flail, Mace, Greatsword, Warhammer, Maul, Long Hammer, Ogre Hook, Horsechopper, Orc Necksplitter, Butchering Axe, War Flail, Scizore, Wrecker<br><img style=\"width:25%;\" src=\"https:\/\/d3a4xjr8r2ldhu.cloudfront.net\/campaigns\/273567\/9d4c082f-a500-44c2-b922-4cf564ee4156.png\" data-gallery-id=\"9d4c082f-a500-44c2-b922-4cf564ee4156\" class=\"note-float-right\" alt=\"9d4c082f-a500-44c2-b922-4cf564ee4156.png\">Cleric Outfit: Bane's clerics wear black iron armor etched with angular designs representing tyranny and domination. Over the armor, they wear a long, dark cloak, and their faces are often hidden by spiked iron helms. A thick, black chain belt hangs around their waist, symbolizing their role in enforcing control and subjugation.<br><\/li><\/ul>","is_private":0,"tooltip":null,"is_template":null,"is_attributes_private":0,"focus_x":null,"focus_y":null,"created_at":"2024-10-18T05:27:33.000000Z","updated_at":"2024-10-21T08:20:14.000000Z","created_by":275646,"updated_by":275646,"image_path":null,"image_uuid":"9d4c0812-fcb8-4dfd-ac0a-865c9e8406b9","header_image":null,"header_uuid":null,"marketplace_uuid":null}}